[{"block": "252924", "color": "bgc-done", "currency_str": "Mastercoin and Test Mastercoin", "details": "1J7Pzq1MvS6ti5YV6dfJ4NW9iZU4uhMEj6", "exodus": true, "formatted_amount": "11.85397321", "from_address": "exodus", "icon": "exodus", "icon_text": "Exodus", "index": "485", "invalid": false, "method": "exodus", "orig_value": "10000000", "to_address": "1J7Pzq1MvS6ti5YV6dfJ4NW9iZU4uhMEj6", "tx_hash": "147687964b3fb41b869505a59a62c78dea78529db21f51439d5822096102add8", "tx_method_str": "exodus", "tx_time": "1376872317000", "tx_type_str": "exodus"}]
