[{"block": "254365", "color": "bgc-done", "currency_str": "Mastercoin and Test Mastercoin", "details": "1RodtRU2EJ7DMgZCjgznivm5yqoeu8Lgh", "exodus": true, "formatted_amount": "474.50662438", "from_address": "exodus", "icon": "exodus", "icon_text": "Exodus", "index": "82", "invalid": false, "method": "exodus", "orig_value": "441750000", "to_address": "1RodtRU2EJ7DMgZCjgznivm5yqoeu8Lgh", "tx_hash": "20e5b8b7b408a433fff1f39fbd4ae4b10de1cdf8b6dd9f31453e0fa14cac3f78", "tx_method_str": "exodus", "tx_time": "1377545129000", "tx_type_str": "exodus"}]
