[{"block": "254187", "color": "bgc-done", "currency_str": "Mastercoin and Test Mastercoin", "details": "1MR9wDhmKVRDcVcpm2c4BB71SR9yTYdBvg", "exodus": true, "formatted_amount": "326.93640873", "from_address": "exodus", "icon": "exodus", "icon_text": "Exodus", "index": "156", "invalid": false, "method": "exodus", "orig_value": "300000000", "to_address": "1MR9wDhmKVRDcVcpm2c4BB71SR9yTYdBvg", "tx_hash": "5383018b76109c5f0c971b90e69e17e7e4c943c166be86d37b4e714a75f7f74a", "tx_method_str": "exodus", "tx_time": "1377450562000", "tx_type_str": "exodus"}]
