[{"block": "255341", "color": "bgc-done", "currency_str": "Mastercoin and Test Mastercoin", "details": "17dkzPoFrkw5V2sDsBqSbbbvygaPzWsz68", "exodus": true, "formatted_amount": "0.50052794", "from_address": "exodus", "icon": "exodus", "icon_text": "Exodus", "index": "80", "invalid": false, "method": "exodus", "orig_value": "500000", "to_address": "17dkzPoFrkw5V2sDsBqSbbbvygaPzWsz68", "tx_hash": "ed7d55147a232b3645f9db8f6b11d0d0dd7b26c14206615564475340054c094e", "tx_method_str": "exodus", "tx_time": "1377987214000", "tx_type_str": "exodus"}]
